[
    {
        "year": "2021",
        "title": "BRAIN AND STRUCTURE LIMITED - RC-1877139 - Nigeria",
        "description": "BRAIN AND STRUCTURE LIMITED Nigeria company, Company number: RC-1877139, Incorporation Date 23. Dez. 2021;, Address: 1 ENGINEERING CLOSE, VICTORIA ISLAND, LAGOS STATE",
        "company": {
            "id": 108702211,
            "name": "BRAIN AND STRUCTURE LIMITED",
            "internationalNumber": "RC-1877139",
            "localNumber": "1877139",
            "countryId": 24,
            "dateCreated": "2021-12-23T00:00:00.000Z",
            "createdAt": "2022-04-11T15:12:32.360Z",
            "updatedAt": "2024-06-15T14:18:14.849Z",
            "alternateNames": [],
            "address": "1 ENGINEERING CLOSE, VICTORIA ISLAND, LAGOS STATE",
            "additionalData": {},
            "typeId": 99330,
            "paidShareCapital": "1000000 NGN",
            "historicalNames": [],
            "activityDescription": "Business Consultancy, IT Consultancy, Communication and General Merchandise",
            "providerId": "7765131",
            "updatedAtSitemap": "2023-06-09T18:11:20.000Z",
            "oldInternationalNumber": "1877139",
            "claimCompanyData": {},
            "country": {
                "id": 24,
                "name": "Nigeria",
                "deadCompanyStatus": [
                    3995958,
                    3995963,
                    3995977,
                    4007873,
                    4007877,
                    4007875
                ],
                "liquidatedCompanyStatus": [
                    3995962,
                    4007878
                ],
                "liquidationCompanyStatus": [
                    4002573,
                    4006402,
                    4007876,
                    4007879,
                    4007881
                ],
                "bankruptcyProcessCompanyStatus": [],
                "reservationCompanyStatus": [],
                "formationCompanyStatus": [],
                "code": "ng",
                "currency": "NGN",
                "sources": [
                    {
                        "url": "https:\/\/www.cac.gov.ng\/",
                        "name": "Corporate Affairs Commission"
                    }
                ],
                "translation": {
                    "en": "Nigeria"
                },
                "fromCountry": {
                    "en": "Nigeria"
                },
                "companiesCount": 4517406,
                "activeCompaniesCount": 690055,
                "restrictedData": {},
                "languages": [
                    "en"
                ]
            },
            "type": {
                "id": 99330,
                "type": "Private company limited by shares",
                "countryId": 24,
                "translation": {
                    "en": "Private company limited by shares"
                },
                "isIndividual": false
            },
            "statuses": [
                {
                    "id": 4007874,
                    "providerId": "ACTIVE",
                    "providerName": "ACTIVE",
                    "countryId": 24,
                    "translation": {
                        "en": "Active"
                    }
                }
            ],
            "accounts": [],
            "tags": [],
            "LEI": [],
            "CIK": [],
            "CAGE": [],
            "companiesRegisteredSameDate": 1195,
            "reviews": [],
            "allReviewsCount": "0",
            "allReviewsRating": "0",
            "categories": [],
            "activities": [
                {
                    "id": 6196948,
                    "providerId": "199238",
                    "providerName": "General Merchandise ",
                    "countryId": 24,
                    "createdAt": "2021-11-07T14:00:34.036647+00:00",
                    "translation": {},
                    "type": {
                        "id": 1,
                        "name": "Primary",
                        "translation": {
                            "en": "Primary activities"
                        }
                    }
                }
            ],
            "addresses": [
                {
                    "id": 88871193,
                    "address": "1 ENGINEERING CLOSE, VICTORIA ISLAND, LAGOS STATE",
                    "countryId": 24,
                    "companies": [
                        {
                            "name": "JOSNICK REALTORS",
                            "internationalNumber": "BN-2603012"
                        },
                        {
                            "name": " VISLAND CONSULTING AND ENGINEERING SERVICES LIMITED ",
                            "internationalNumber": "RC-1776212"
                        },
                        {
                            "name": "BAKER SMITH CONSULTING SERVICES",
                            "internationalNumber": "BN-3413397"
                        },
                        {
                            "name": "TOPBANC",
                            "internationalNumber": "BN-2568810"
                        },
                        {
                            "name": "PILLS ON WHEELS MEDICAL SERVICES LTD",
                            "internationalNumber": "RC-1827110"
                        },
                        {
                            "name": "YUNITAL CONSTRUCTION COMPANY LIMITED",
                            "internationalNumber": "RC-1289546"
                        }
                    ]
                }
            ],
            "persons": [
                {
                    "id": 339765420,
                    "companyId": 108702211,
                    "personId": 67876549,
                    "roleId": 114332,
                    "sourceNum": 1,
                    "person": {
                        "id": 67876549,
                        "name": "kehinde isreal adedoyin",
                        "countryId": 24,
                        "nationality": "NIGERIAN",
                        "birthYear": 1993,
                        "birthMonth": 1,
                        "birthDate": 11,
                        "address": "Akeem OdumosuMagodo Isheri, Magodo, LAGOS STATE",
                        "countryOfResidence": "NIGERIA",
                        "number": "3630739",
                        "documentType": "International Passport",
                        "documentNumber": "A04299578",
                        "email": "kehindeisreal2@gmail.com",
                        "phone": "+234 818 622 5421",
                        "countryCode": "ng",
                        "countryTranslation": {
                            "cs": "Nigeria",
                            "de": "Nigeria",
                            "en": "Nigeria",
                            "es": "Nigeria",
                            "fr": "Nigeria",
                            "lt": "Nigerija",
                            "lv": "Nig\u0113rija",
                            "nl": "Nigeria",
                            "pl": "Nigeria",
                            "ro": "Nigeria",
                            "ru": "\u041d\u0438\u0433\u0435\u0440\u0438\u044f",
                            "tr": "Nijerya",
                            "uk": "\u041d\u0456\u0433\u0435\u0440\u0456\u044f",
                            "zh": "\u5c3c\u65e5\u5229\u4e9a"
                        }
                    },
                    "role": {
                        "id": 114332,
                        "name": "Legal Practitioner",
                        "countryId": 24,
                        "translation": {
                            "en": "Legal Practitioner"
                        },
                        "priority": 3
                    },
                    "companies": [
                        {
                            "name": "MATARVAH LTD",
                            "internationalNumber": "RC-1806330"
                        },
                        {
                            "name": "EVERYTHING SAVVY",
                            "internationalNumber": "BN-3472603"
                        },
                        {
                            "name": "THE DESHAPEABLES CONCEPT LIMITED",
                            "internationalNumber": "RC-1807768"
                        },
                        {
                            "name": "FEEBEE SPARKLE",
                            "internationalNumber": "BN-3447517"
                        },
                        {
                            "name": "RELLA'S THERAPY",
                            "internationalNumber": "BN-3428808"
                        },
                        {
                            "name": "GAHAWARDS LTD",
                            "internationalNumber": "RC-1841561"
                        },
                        {
                            "name": "TAAMA PAP",
                            "internationalNumber": "BN-3428048"
                        },
                        {
                            "name": "PURE FRUITS AND FOODS",
                            "internationalNumber": "BN-3437250"
                        },
                        {
                            "name": "ESSENTRA FARMS",
                            "internationalNumber": "BN-3476379"
                        },
                        {
                            "name": "VASHTYVAIN",
                            "internationalNumber": "BN-3403219"
                        },
                        {
                            "name": "MILENAR DESIGN",
                            "internationalNumber": "BN-3555171"
                        },
                        {
                            "name": "PEOSA NATURAL ENTERPRISE",
                            "internationalNumber": "BN-3404507"
                        },
                        {
                            "name": "BLUE DIAMOND COLLECTIONS",
                            "internationalNumber": "BN-3383319"
                        },
                        {
                            "name": "TABITHA HAIR AND WIGTOOLS",
                            "internationalNumber": "BN-3398781"
                        },
                        {
                            "name": "THE DEKIDABLES CONCEPT LIMITED",
                            "internationalNumber": "RC-1808387"
                        },
                        {
                            "name": "CHRISTINE ORGANIC SKINCARE",
                            "internationalNumber": "BN-3421616"
                        }
                    ],
                    "naturesOfControl": [],
                    "personShares": []
                }
            ],
            "companyContacts": {
                "email": [
                    "mke*****************"
                ]
            },
            "companyContactPersons": [
                {
                    "name": "Keh**** Isr*** Ade*****",
                    "contacts": {
                        "phone": [
                            "+23**************",
                            "081********"
                        ],
                        "email": [
                            "keh*********************"
                        ]
                    }
                },
                {
                    "name": "Ade***** Isr*** Keh****",
                    "contacts": {
                        "email": [
                            "keh*********************"
                        ],
                        "phone": [
                            "+23**************"
                        ]
                    }
                }
            ],
            "shares": [],
            "financialReports": "[]",
            "permits": [],
            "licenses": [],
            "inspections": [],
            "subdivisions": [],
            "insolvencies": [],
            "events": [],
            "history": [],
            "links": [],
            "vehicles": [],
            "restrictions": [],
            "courtCases": [],
            "acquisitions": [],
            "securityMeasures": [],
            "companyDocuments": [],
            "filings": [],
            "charges": [],
            "affiliates": [],
            "listTags": [],
            "inspectionsCount": 0,
            "permitsCount": 0,
            "licensesCount": 0,
            "subdivisionsCount": 0,
            "insolvenciesCount": 0,
            "eventsCount": 0,
            "historyCount": 0,
            "linksCount": 0,
            "companyVehiclesCount": 0,
            "restrictionsCount": 0,
            "courtCasesCount": 0,
            "acquisitionsCount": 0,
            "securityMeasuresCount": 0,
            "companyDocumentsCount": 0,
            "filingsCount": 0,
            "chargesCount": 0,
            "affiliatesCount": "0",
            "personsCount": "1",
            "companyContactsCount": 1,
            "companyContactPersonsCount": 5,
            "personsCountByPriority": {
                "3": 1
            },
            "personsWithRelatedCount": 1
        }
    }
]