[
    {
        "year": "2021",
        "title": "Lord & Lux Capital Assets Ltd - RC-1876316 - Nigeria",
        "description": "Lord & Lux Capital Assets Ltd Nigeria company, Company number: RC-1876316, Incorporation Date 22 \u0433\u0440\u0443\u0434 2021 \u0440.;, Address: NO. 28 JIMOH BALOGUN STREET, OFF CMD ROAD, IKOSI-KETU, LAGOS STATE",
        "company": {
            "id": 108700497,
            "name": "Lord & Lux Capital Assets Ltd",
            "internationalNumber": "RC-1876316",
            "localNumber": "1876316",
            "countryId": 24,
            "dateCreated": "2021-12-22T00:00:00.000Z",
            "createdAt": "2022-04-11T13:47:24.368Z",
            "updatedAt": "2024-06-15T14:18:20.342Z",
            "alternateNames": [],
            "address": "NO. 28 JIMOH BALOGUN STREET, OFF CMD ROAD, IKOSI-KETU, LAGOS STATE",
            "additionalData": {},
            "typeId": 99330,
            "paidShareCapital": "1000000 NGN",
            "historicalNames": [],
            "activityDescription": "To acquire, sell, lease, let or otherwise permit the use of and to hold, improve, alter, develop, sell or otherwise dispose of buildings, accommodation, lands and all properties describable as real estate (whether or not this is done on behalf of other persons).",
            "providerId": "7763477",
            "updatedAtSitemap": "2023-06-09T18:11:40.000Z",
            "oldInternationalNumber": "1876316",
            "claimCompanyData": {},
            "country": {
                "id": 24,
                "name": "Nigeria",
                "deadCompanyStatus": [
                    3995958,
                    3995963,
                    3995977,
                    4007873,
                    4007877,
                    4007875
                ],
                "liquidatedCompanyStatus": [
                    3995962,
                    4007878
                ],
                "liquidationCompanyStatus": [
                    4002573,
                    4006402,
                    4007876,
                    4007879,
                    4007881
                ],
                "bankruptcyProcessCompanyStatus": [],
                "reservationCompanyStatus": [],
                "formationCompanyStatus": [],
                "code": "ng",
                "currency": "NGN",
                "sources": [
                    {
                        "url": "https:\/\/www.cac.gov.ng\/",
                        "name": "Corporate Affairs Commission"
                    }
                ],
                "translation": {
                    "en": "Nigeria"
                },
                "fromCountry": {
                    "en": "Nigeria"
                },
                "companiesCount": 4517406,
                "activeCompaniesCount": 690055,
                "restrictedData": {},
                "languages": [
                    "en"
                ]
            },
            "type": {
                "id": 99330,
                "type": "Private company limited by shares",
                "countryId": 24,
                "translation": {
                    "en": "Private company limited by shares"
                },
                "isIndividual": false
            },
            "statuses": [
                {
                    "id": 4007874,
                    "providerId": "ACTIVE",
                    "providerName": "ACTIVE",
                    "countryId": 24,
                    "translation": {
                        "en": "Active"
                    }
                }
            ],
            "accounts": [],
            "tags": [],
            "LEI": [],
            "CIK": [],
            "CAGE": [],
            "companiesRegisteredSameDate": 1455,
            "reviews": [],
            "allReviewsCount": "0",
            "allReviewsRating": "0",
            "categories": [],
            "activities": [
                {
                    "id": 6197314,
                    "providerId": "143244",
                    "providerName": "Real estate activities.",
                    "countryId": 24,
                    "createdAt": "2021-11-07T14:08:42.830882+00:00",
                    "translation": {},
                    "type": {
                        "id": 1,
                        "name": "Primary",
                        "translation": {
                            "en": "Primary activities"
                        }
                    }
                }
            ],
            "addresses": [
                {
                    "id": 96001090,
                    "address": "NO. 28 JIMOH BALOGUN STREET, OFF CMD ROAD, IKOSI-KETU, LAGOS STATE",
                    "countryId": 24,
                    "companies": []
                }
            ],
            "persons": [
                {
                    "id": 339715210,
                    "companyId": 108700497,
                    "personId": 92573665,
                    "roleId": 114332,
                    "sourceNum": 1,
                    "person": {
                        "id": 92573665,
                        "name": "'sogo oluwasogo oyelami",
                        "countryId": 24,
                        "nationality": "NIGERIAN",
                        "birthYear": 1982,
                        "birthMonth": 10,
                        "birthDate": 24,
                        "address": "4BAgbaoku Street, Opebi, LAGOS STATE",
                        "countryOfResidence": "NIGERIA",
                        "number": "1321561",
                        "documentType": "Driver's License",
                        "documentNumber": "FKJ74416AA03",
                        "email": "sogo.oyelami@gmail.com",
                        "phone": "+234 806 803 6376",
                        "countryCode": "ng",
                        "countryTranslation": {
                            "cs": "Nigeria",
                            "de": "Nigeria",
                            "en": "Nigeria",
                            "es": "Nigeria",
                            "fr": "Nigeria",
                            "lt": "Nigerija",
                            "lv": "Nig\u0113rija",
                            "nl": "Nigeria",
                            "pl": "Nigeria",
                            "ro": "Nigeria",
                            "ru": "\u041d\u0438\u0433\u0435\u0440\u0438\u044f",
                            "tr": "Nijerya",
                            "uk": "\u041d\u0456\u0433\u0435\u0440\u0456\u044f",
                            "zh": "\u5c3c\u65e5\u5229\u4e9a"
                        }
                    },
                    "role": {
                        "id": 114332,
                        "name": "Legal Practitioner",
                        "countryId": 24,
                        "translation": {
                            "en": "Legal Practitioner"
                        },
                        "priority": 3
                    },
                    "companies": [
                        {
                            "name": "MYMUSE BUSINESS DEVELOPMENT COMPANY LTD",
                            "internationalNumber": "RC-1373654"
                        },
                        {
                            "name": "BUCAK INVT NIG LIMITED",
                            "internationalNumber": "RC-1475164"
                        },
                        {
                            "name": "SHANOLLS GLOBAL SERVICES",
                            "internationalNumber": "BN-2459060"
                        },
                        {
                            "name": "DIGICLOUD SOLUTIONS LIMITED",
                            "internationalNumber": "RC-1358144"
                        },
                        {
                            "name": "MIRIAMS'DELIGHT CAKES AND MORE",
                            "internationalNumber": "BN-2574707"
                        },
                        {
                            "name": "KOSECCA AGRO INDUSTRIES LTD",
                            "internationalNumber": "RC-1329987"
                        },
                        {
                            "name": "FOX CAPITAL INVESTMENTS LIMITED",
                            "internationalNumber": "RC-1378723"
                        },
                        {
                            "name": "VELOFORCEIT TECHNOLOGY LIMITED",
                            "internationalNumber": "RC-1357379"
                        },
                        {
                            "name": "DELUXE VALUE MULTI CONCEPTS",
                            "internationalNumber": "BN-2430810"
                        },
                        {
                            "name": "FIRST CORPORATE FINDERS ASSOCIATES",
                            "internationalNumber": "BN-2585352"
                        },
                        {
                            "name": "LUEBO TECHNOLOGIES LTD",
                            "internationalNumber": "RC-1415017"
                        },
                        {
                            "name": "GODSTIME SALON & BOUTIQUE ENTERPRISES",
                            "internationalNumber": "BN-2468469"
                        },
                        {
                            "name": "TACOT INTERNATIONAL LIMITED",
                            "internationalNumber": "RC-1675827"
                        },
                        {
                            "name": "MIND OF A STYLIST",
                            "internationalNumber": "BN-2368407"
                        },
                        {
                            "name": "FUNSHOGRACE IDENTITY",
                            "internationalNumber": "BN-2575446"
                        },
                        {
                            "name": "THE WISEMASTER ACADEMY",
                            "internationalNumber": "BN-2361216"
                        },
                        {
                            "name": "AFFINITY ART GALLERY LTD",
                            "internationalNumber": "RC-1446062"
                        },
                        {
                            "name": "OBA BUILDING AND CONSTRUCTION PROJECTS LTD",
                            "internationalNumber": "RC-1411081"
                        },
                        {
                            "name": "DELTA6IX LIMITED",
                            "internationalNumber": "RC-1411636"
                        },
                        {
                            "name": "INSIGHTFUL BUSINESS ANALYTICS LTD",
                            "internationalNumber": "RC-1340980"
                        }
                    ],
                    "naturesOfControl": [],
                    "personShares": []
                }
            ],
            "companyContacts": {
                "email": [
                    "lor***************"
                ]
            },
            "companyContactPersons": [
                {
                    "name": "'so** Olu****** Oye****",
                    "contacts": {
                        "email": [
                            "sog*******************"
                        ],
                        "phone": [
                            "+23**************",
                            "080********"
                        ]
                    }
                }
            ],
            "shares": [],
            "financialReports": "[]",
            "permits": [],
            "licenses": [],
            "inspections": [],
            "subdivisions": [],
            "insolvencies": [],
            "events": [],
            "history": [],
            "links": [],
            "vehicles": [],
            "restrictions": [],
            "courtCases": [],
            "acquisitions": [],
            "securityMeasures": [],
            "companyDocuments": [],
            "filings": [],
            "charges": [],
            "affiliates": [],
            "listTags": [],
            "inspectionsCount": 0,
            "permitsCount": 0,
            "licensesCount": 0,
            "subdivisionsCount": 0,
            "insolvenciesCount": 0,
            "eventsCount": 0,
            "historyCount": 0,
            "linksCount": 0,
            "companyVehiclesCount": 0,
            "restrictionsCount": 0,
            "courtCasesCount": 0,
            "acquisitionsCount": 0,
            "securityMeasuresCount": 0,
            "companyDocumentsCount": 0,
            "filingsCount": 0,
            "chargesCount": 0,
            "affiliatesCount": "0",
            "personsCount": "1",
            "companyContactsCount": 1,
            "companyContactPersonsCount": 3,
            "personsCountByPriority": {
                "3": 1
            },
            "personsWithRelatedCount": 1
        }
    }
]