[
    {
        "year": "2022",
        "title": "XHIMPERIAL - BN-3695999 - Nigeria",
        "description": "XHIMPERIAL Nigeria company, Company number: BN-3695999, Incorporation Date 29. \u010dvn 2022;, Address: 19 ADEWUSI STREET, FADEYI, LAGOS STATE, FADEYI, LAGOS STATE",
        "company": {
            "id": 177098752,
            "name": "XHIMPERIAL",
            "internationalNumber": "BN-3695999",
            "localNumber": "3695999",
            "countryId": 24,
            "dateCreated": "2022-06-29T00:00:00.000Z",
            "createdAt": "2022-11-09T10:28:10.838Z",
            "updatedAt": "2024-06-15T14:40:40.967Z",
            "alternateNames": [],
            "address": "19 ADEWUSI STREET, FADEYI, LAGOS STATE, FADEYI, LAGOS STATE",
            "additionalData": {},
            "typeId": 99332,
            "historicalNames": [],
            "providerId": "5911635",
            "updatedAtSitemap": "2023-06-09T20:04:46.000Z",
            "claimCompanyData": {},
            "country": {
                "id": 24,
                "name": "Nigeria",
                "deadCompanyStatus": [
                    3995958,
                    3995963,
                    3995977,
                    4007873,
                    4007877,
                    4007875
                ],
                "liquidatedCompanyStatus": [
                    3995962,
                    4007878
                ],
                "liquidationCompanyStatus": [
                    4002573,
                    4006402,
                    4007876,
                    4007879,
                    4007881
                ],
                "bankruptcyProcessCompanyStatus": [],
                "reservationCompanyStatus": [],
                "formationCompanyStatus": [],
                "code": "ng",
                "currency": "NGN",
                "sources": [
                    {
                        "url": "https:\/\/www.cac.gov.ng\/",
                        "name": "Corporate Affairs Commission"
                    }
                ],
                "translation": {
                    "en": "Nigeria"
                },
                "fromCountry": {
                    "en": "Nigeria"
                },
                "companiesCount": 4517406,
                "activeCompaniesCount": 690055,
                "restrictedData": {},
                "languages": [
                    "en"
                ]
            },
            "type": {
                "id": 99332,
                "type": "Business name - partnership",
                "countryId": 24,
                "translation": {
                    "en": "Partnership"
                },
                "isIndividual": false
            },
            "statuses": [
                {
                    "id": 4007874,
                    "providerId": "ACTIVE",
                    "providerName": "ACTIVE",
                    "countryId": 24,
                    "translation": {
                        "en": "Active"
                    }
                }
            ],
            "accounts": [],
            "tags": [],
            "LEI": [],
            "CIK": [],
            "CAGE": [],
            "companiesRegisteredSameDate": 19,
            "reviews": [],
            "allReviewsCount": "0",
            "allReviewsRating": "0",
            "categories": [],
            "activities": [
                {
                    "id": 6197102,
                    "providerId": "199230",
                    "providerName": "EVENTS MANAGEMENT, GENERAL MERCHANDISE, WHOLESALE AND RETAIL TRADE",
                    "countryId": 24,
                    "createdAt": "2021-11-07T14:03:30.111946+00:00",
                    "translation": {},
                    "type": {
                        "id": 1,
                        "name": "Primary",
                        "translation": {
                            "en": "Primary activities"
                        }
                    }
                }
            ],
            "addresses": [
                {
                    "id": 101704238,
                    "address": "19 ADEWUSI STREET, FADEYI, LAGOS STATE, FADEYI, LAGOS STATE",
                    "countryId": 24,
                    "companies": []
                }
            ],
            "persons": [
                {
                    "id": 365090205,
                    "companyId": 177098752,
                    "personId": 143479518,
                    "roleId": 114458,
                    "sourceNum": 1,
                    "person": {
                        "id": 143479518,
                        "name": "rebecca ibukun olajide",
                        "countryId": 24,
                        "nationality": "NIGERIAN",
                        "birthYear": 1999,
                        "birthMonth": 12,
                        "birthDate": 12,
                        "address": "19Adewusi street, Fadeyi, LAGOS STATE",
                        "countryOfResidence": "NIGERIA",
                        "number": "2754792",
                        "documentType": "Permanent Voters' Card",
                        "documentNumber": "FA5B 3EC3 6A53 5140 379",
                        "email": "xhimperial@gmail.com",
                        "phone": "+234 916 023 6213",
                        "countryCode": "ng",
                        "countryTranslation": {
                            "cs": "Nigeria",
                            "de": "Nigeria",
                            "en": "Nigeria",
                            "es": "Nigeria",
                            "fr": "Nigeria",
                            "lt": "Nigerija",
                            "lv": "Nig\u0113rija",
                            "nl": "Nigeria",
                            "pl": "Nigeria",
                            "ro": "Nigeria",
                            "ru": "\u041d\u0438\u0433\u0435\u0440\u0438\u044f",
                            "tr": "Nijerya",
                            "uk": "\u041d\u0456\u0433\u0435\u0440\u0456\u044f",
                            "zh": "\u5c3c\u65e5\u5229\u4e9a"
                        }
                    },
                    "role": {
                        "id": 114458,
                        "name": "Student",
                        "countryId": 24,
                        "translation": {
                            "en": ""
                        }
                    },
                    "companies": [],
                    "naturesOfControl": [],
                    "personShares": []
                }
            ],
            "companyContacts": {
                "email": [
                    "xhi*****************"
                ]
            },
            "companyContactPersons": [
                {
                    "name": "Reb**** Ibu*** Ola****",
                    "contacts": {
                        "email": [
                            "xhi*****************"
                        ],
                        "phone": [
                            "+23**************"
                        ]
                    }
                }
            ],
            "shares": [],
            "financialReports": "[]",
            "permits": [],
            "licenses": [],
            "inspections": [],
            "subdivisions": [],
            "insolvencies": [],
            "events": [],
            "history": [],
            "links": [],
            "vehicles": [],
            "restrictions": [],
            "courtCases": [],
            "acquisitions": [],
            "securityMeasures": [],
            "companyDocuments": [],
            "filings": [],
            "charges": [],
            "affiliates": [],
            "listTags": [],
            "inspectionsCount": 0,
            "permitsCount": 0,
            "licensesCount": 0,
            "subdivisionsCount": 0,
            "insolvenciesCount": 0,
            "eventsCount": 0,
            "historyCount": 0,
            "linksCount": 0,
            "companyVehiclesCount": 0,
            "restrictionsCount": 0,
            "courtCasesCount": 0,
            "acquisitionsCount": 0,
            "securityMeasuresCount": 0,
            "companyDocumentsCount": 0,
            "filingsCount": 0,
            "chargesCount": 0,
            "affiliatesCount": "0",
            "personsCount": "1",
            "companyContactsCount": 1,
            "companyContactPersonsCount": 2,
            "personsCountByPriority": {
                "null": 1
            },
            "personsWithRelatedCount": 0
        }
    }
]